{
  "slug": "youtube-cpm-calculator",
  "title": "Calculadora de CPM de YouTube 2026 — De CPM a RPM | Kalkil",
  "metaDescription": "Calculadora gratuita de CPM de YouTube. Comprende la diferencia entre CPM y RPM y calcula tus ingresos reales como creador. Resultados al instante.",
  "ogTitle": "Calculadora de CPM de YouTube 2026 — De CPM a RPM | Kalkil",
  "ogDescription": "Calculadora gratuita de CPM de YouTube. Comprende la diferencia entre CPM y RPM y calcula tus ingresos reales como creador. Resultados al instante.",
  "nodes": [
    { "id": "t0", "text": "▶ YouTube · Calculadora de CPM → RPM" },
    { "id": "t1", "text": "Calculadora de CPM" },
    { "id": "t2", "text": "de YouTube" },
    { "id": "t3", "text": "Convierte el CPM en RPM y descubre exactamente cuánto te queda después del 45% que retiene YouTube." },
    { "id": "t4", "text": "Inicio" },
    { "id": "t5", "text": "›" },
    { "id": "t6", "text": "Calculadoras" },
    { "id": "t7", "text": "›" },
    { "id": "t8", "text": "Calculadora de CPM de YouTube 2026 — De CPM a RPM" },
    { "id": "t9", "text": "✓ Gratis · Sin registro · Resultados al instante" },
    { "id": "t10", "text": "Vistas totales del video" },
    { "id": "t11", "text": "Tarifa de CPM ($)" },
    { "id": "t12", "text": "Es lo que pagan los anunciantes por cada 1,000 impresiones de anuncios" },
    { "id": "t13", "text": "Tasa de monetización (%)" },
    { "id": "t14", "text": "% de vistas que muestran un anuncio (normalmente 70–90%)" },
    { "id": "t15", "text": "Calcular" },
    { "id": "t16", "text": "Restablecer" },
    { "id": "t17", "text": "Ingresos brutos por publicidad" },
    { "id": "t18", "text": "Antes del 45% que se queda YouTube" },
    { "id": "t19", "text": "Tu RPM" },
    { "id": "t20", "text": "Neto por cada 1,000 vistas totales" },
    { "id": "t21", "text": "Ganancias netas (lo que te queda)" },
    { "id": "t22", "text": "55% de los ingresos brutos por publicidad" },
    { "id": "t23", "text": "Anual (×12)" },
    { "id": "t24", "text": "Si esta es tu tasa mensual de vistas" },
    { "id": "t25", "text": "CPM vs. RPM: ¿cuál es la diferencia?" },
    { "id": "t26", "text": "CPM" },
    { "id": "t27", "text": "(costo por mil) es lo que los anunciantes le pagan a YouTube por cada 1,000 impresiones de anuncios en tu contenido. Es la tarifa bruta, antes de que YouTube se quede con su parte." },
    { "id": "t28", "text": "RPM" },
    { "id": "t29", "text": "(ingresos por mil) es lo que realmente recibes por cada 1,000 vistas totales del video, después del 45% que se queda YouTube y teniendo en cuenta que no todas las vistas muestran un anuncio." },
    { "id": "t30", "text": "Fórmula clave: RPM = CPM × 0.55 × tasa de monetización" },
    { "id": "t31", "text": "Ejemplo: CPM de $10 × 0.55 × 0.80 de monetización =" },
    { "id": "t32", "text": "$4.40 de RPM" },
    { "id": "t33", "text": "Por qué importa tu tasa de monetización" },
    { "id": "t34", "text": "Los bloqueadores de anuncios reducen tu tasa de monetización efectiva" },
    { "id": "t35", "text": "Los espectadores que saltan los anuncios de inmediato no generan el ingreso completo" },
    { "id": "t36", "text": "El contenido no monetizado (música, reclamos de derechos de autor) no genera ingresos" },
    { "id": "t37", "text": "La mayoría de los canales tiene, en la práctica, tasas de monetización del 70–85%" },
    { "id": "t38", "text": "¿Quieres entender los números?" },
    { "id": "t39", "text": "Lee nuestra guía gratuita y detallada que explica exactamente cómo esta plataforma les paga a los creadores." },
    { "id": "t40", "text": "Leer la guía →" },
    { "id": "t41", "text": "Más calculadoras" },
    { "id": "t42", "text": "▶" },
    { "id": "t43", "text": "Calculadora de YouTube" },
    { "id": "t44", "text": "Ingresos de AdSense y CPM" },
    { "id": "t45", "text": "⚡" },
    { "id": "t46", "text": "Calculadora de YouTube Shorts" },
    { "id": "t47", "text": "RPM de Shorts vs. videos largos" },
    { "id": "t48", "text": "🤝" },
    { "id": "t49", "text": "Calculadora de patrocinios" },
    { "id": "t50", "text": "Valor de acuerdos con marcas" },
    { "id": "t51", "text": "♪" },
    { "id": "t52", "text": "Calculadora de TikTok" },
    { "id": "t53", "text": "Creator Rewards + acuerdos de marca" },
    { "id": "t54", "text": "Kalkil Pro" },
    { "id": "t55", "text": "Consulta todos tus ingresos en un solo lugar" },
    { "id": "t56", "text": "YouTube, Spotify, TikTok, Twitch y más: un panel unificado con comparativas y proyecciones." },
    { "id": "t57", "text": "Probar Kalkil Pro gratis →" },
    { "id": "t58", "text": "Gratis para empezar · No requiere tarjeta de crédito" }
  ]
}
